flycheap/__init__.py
flycheap/_airline.csv
flycheap/_airport.csv
flycheap/_throughput.csv
flycheap/civilaviation.py
flycheap/ctripcrawler.py
flycheap/rebuilder.py
flycheap-0.1.7.dist-info/LICENSE
flycheap-0.1.7.dist-info/METADATA
flycheap-0.1.7.dist-info/WHEEL
flycheap-0.1.7.dist-info/top_level.txt
flycheap-0.1.7.dist-info/RECORD
