Metadata-Version: 2.1
Name: flycheap
Version: 0.1.7
Summary: Flight Tickets Price Collection, Statistics and Analysis based on ctrip.com
Home-page: https://github.com/LF502/FlyCheap
Author: Primarie
Author-email: SyzygyPrimarie@gmail.com
License: UNKNOWN
Platform: UNKNOWN
Classifier: Programming Language :: Python :: 3
Classifier: License :: OSI Approved :: MIT License
Classifier: Operating System :: OS Independent
Requires-Python: >=3.6
License-File: LICENSE
Requires-Dist: requests
Requires-Dist: json5
Requires-Dist: openpyxl
Requires-Dist: pandas
